autofeatinsights/Autofeat.py
autofeatinsights/__init__.py
autofeatinsights-0.0.1.dev2.dist-info/METADATA
autofeatinsights-0.0.1.dev2.dist-info/WHEEL
autofeatinsights-0.0.1.dev2.dist-info/licenses/LICENSE
autofeatinsights-0.0.1.dev2.dist-info/RECORD
