Metadata-Version: 2.1
Name: autofeatinsights
Version: 0.0.1.dev2
Summary: Insights for AutoFeat
Project-URL: Homepage, https://github.com/zegermouw/autofeat_insights
Project-URL: Issues, https://github.com/zegermouw/autofeat_insights/issues
Author-email: Zeger Mouw <zegermouw@gmail.com>
License-File: LICENSE
Classifier: License :: OSI Approved :: MIT License
Classifier: Operating System :: OS Independent
Classifier: Programming Language :: Python :: 3
Requires-Python: >=3.8
